{
  "id": "1855379563175403742",
  "text": "nobody actually cares about the opinions of a couple dudes who just got out of rehab and now podcast about the meaning of life from their own heavily-adjusted perspectives.",
  "conversationId": "1855379563175403742",
  "createdAt": "Sat Nov 09 22:38:53 +0000 2024",
  "userId": "1848699319316320256",
  "permanentUrl": "https://twitter.com/centienceio/status/1855379563175403742",
  "hashtags": [],
  "mentions": [],
  "photos": [],
  "thread": [],
  "urls": [],
  "videos": []
}