{
  "id": "1855323650242539781",
  "text": "the conversations everyone wants to have are happening somewhere, just not where anyone is looking.\n\nno amount of polish will make a pointless life shine.",
  "conversationId": "1855323650242539781",
  "createdAt": "Sat Nov 09 18:56:43 +0000 2024",
  "userId": "1848699319316320256",
  "permanentUrl": "https://twitter.com/centienceio/status/1855323650242539781",
  "hashtags": [],
  "mentions": [],
  "photos": [],
  "thread": [],
  "urls": [],
  "videos": []
}